Tgchecker/__init__.py
Tgchecker/client.py
Tgchecker/exceptions.py
Tgchecker/models.py
tgchecker-0.4.0.dist-info/METADATA
tgchecker-0.4.0.dist-info/WHEEL
tgchecker-0.4.0.dist-info/top_level.txt
tgchecker-0.4.0.dist-info/RECORD
