Metadata-Version: 2.4
Name: Tgchecker
Version: 0.4.0
Summary: Telegram number checker
Author: Irbots
License: MIT
Project-URL: Homepage, https://irbots.com/TG-Number-Analyzer/
Requires-Python: >=3.10
Requires-Dist: httpx
